README.rst
setup.cfg
setup.py
./__init__.py
./carrier.py
./carrier.xml
./configuration.py
./location.py
./location.xml
./log.py
./manifest.py
./manifest.xml
./mixin.py
./package.py
./party.py
./party.xml
./sale.py
./sale.xml
./shipment.py
./shipment.xml
./stock.py
./tracking.py
./tryton.cfg
./locale/de_DE.po
./tests/__init__.py
./tests/test_party.py
./tests/test_shipping.py
./tests/test_views_depends.py
./view/address_form.xml
./view/address_suggestion_form.xml
./view/address_validation_end_form.xml
./view/apply_shipping_select_rate_form.xml
./view/apply_shipping_start_form.xml
./view/box_type_form.xml
./view/box_type_tree.xml
./view/carrier_form.xml
./view/carrier_service_view_form.xml
./view/carrier_service_view_tree.xml
./view/carrier_tree.xml
./view/generate_shipping_label_message_view_form.xml
./view/generate_shipping_label_wizard_start_view_form.xml
./view/location_form.xml
./view/manifest_view_form.xml
./view/manifest_view_tree.xml
./view/no_module_form.xml
./view/package_form.xml
./view/package_tree.xml
./view/party_configuration_form.xml
./view/sale_view_form.xml
./view/select_rate_view_form.xml
./view/shipment_out_form.xml
./view/shipment_out_tree.xml
./view/shipment_tracking_form.xml
./view/shipment_tracking_tree.xml
fio_shipping.egg-info/PKG-INFO
fio_shipping.egg-info/SOURCES.txt
fio_shipping.egg-info/dependency_links.txt
fio_shipping.egg-info/entry_points.txt
fio_shipping.egg-info/not-zip-safe
fio_shipping.egg-info/requires.txt
fio_shipping.egg-info/top_level.txt